main.py
gigachain_elasticsearch-100.0.0.dist-info/METADATA
gigachain_elasticsearch-100.0.0.dist-info/WHEEL
gigachain_elasticsearch-100.0.0.dist-info/top_level.txt
gigachain_elasticsearch-100.0.0.dist-info/RECORD
